{"data":{"postsJson":{"title":"Dos Nacimientos MIlagrosos","questionsTitle":"COMPARACIÓN, CONTRASTE & REPETICIÓN","display":"block","bookName":"Lucas","ref":"1:1-2:40","html":"<p>   <strong>1</strong><u>1</u>Muchas personas han intentado escribir un relato de los hechos que se han cumplido entre nosotros. <u>2</u>Se valieron de los informes que circulan entre nosotros dados por testigos oculares, los primeros discípulos.* <u>3</u>Después de investigar todo con esmero desde el principio, yo también decidí escribir un relato cuidadoso para ti, muy honorable Teófilo, <u>4</u>para que puedas estar seguro de la veracidad de todo lo que te han enseñado.<br />   <u>5</u>Cuando Herodes era rey en Judea, hubo un sacerdote judío llamado Zacarías. Era miembro del grupo sacerdotal de Abías; y su esposa, Elisabet, también pertenecía a la familia sacerdotal de Aarón. <u>6</u>Zacarías y Elisabet eran justos a los ojos de Dios y cuidadosos en obedecer todos los mandamientos y las ordenanzas del Señor. <u>7</u>No tenían hijos porque Elisabet no podía quedar embarazada y los dos eran ya muy ancianos.<br />   <u>8</u>Cierto día, Zacarías se encontraba sirviendo a Dios en el templo, porque su grupo de sacerdotes estaba de turno esa semana. <u>9</u>Como era costumbre entre los sacerdotes, le tocó por sorteo entrar en el santuario del Señor y quemar el incienso. <u>10</u>Mientras el incienso se quemaba, una gran multitud estaba afuera orando.<br />   <u>11</u>Y mientras Zacarías estaba en el santuario, se le apareció un ángel del Señor, de pie a la derecha del altar del incienso. <u>12</u>Cuando Zacarías lo vio, se alarmó y se llenó de temor, <u>13</u>pero el ángel le dijo:</p><h1>GABRIEL</h1><h4> —¡No tengas miedo, Zacarías! Dios ha oído tu oración. Tu esposa, Elisabet, te dará un hijo, y lo llamarás Juan. <u>14</u>Tendrás gran gozo y alegría, y muchos se alegrarán de su nacimiento, <u>15</u>porque él será grande a los ojos del Señor. No deberá beber vino ni ninguna bebida alcohólica y será lleno del Espíritu Santo aun antes de nacer.* <u>16</u>Y hará que muchos israelitas vuelvan al Señor su Dios. <u>17</u>Será un hombre con el espíritu y el poder de Elías; preparará a la gente para la venida del Señor. Inclinará el corazón de los padres* hacia los hijos* y hará que los rebeldes acepten la sabiduría de los justos.</h4><p>   <u>18</u>Zacarías le dijo al ángel:</p><h1>ZACARÍAS</h1><h4> —¿Cómo puedo estar seguro de que ocurrirá esto? Ya soy muy anciano, y mi esposa también es de edad avanzada.</h4><p>   <u>19</u>Entonces el ángel dijo:</p><h1>GABRIEL</h1><h4> —¡Yo soy Gabriel! Estoy en la presencia misma de Dios. ¡Fue él quien me envió a darte esta buena noticia! <u>20</u>Pero ahora, como no creíste lo que te dije, te quedarás mudo, sin poder hablar hasta que nazca el niño. Te aseguro que mis palabras se cumplirán a su debido tiempo.</h4><p>   <u>21</u>Mientras tanto, la gente esperaba a que Zacarías saliera del santuario y se preguntaba por qué tardaba tanto. <u>22</u>Cuando por fin salió, no podía hablarles. Entonces, por las señas que hacía y su silencio, se dieron cuenta de que seguramente había tenido una visión en el santuario.<br />   <u>23</u>Cuando Zacarías terminó su semana de servicio en el templo, regresó a su casa. <u>24</u>Poco tiempo después, su esposa, Elisabet, quedó embarazada y permaneció recluida en su casa durante cinco meses. </p><h1>ELISABET</h1><h4><u>25</u>«¡Qué bondadoso es el Señor! </h4><p>—exclamó ella—. </p><h1>ELISABET</h1><h4>Me ha quitado la vergüenza de no tener hijos».</h4><p>   <u>26</u>Cuando Elisabet estaba en su sexto mes de embarazo, Dios envió al ángel Gabriel a Nazaret, una aldea de Galilea, <u>27</u>a una virgen llamada María. Ella estaba comprometida para casarse con un hombre llamado José, descendiente del rey David. <u>28</u>Gabriel se le apareció y dijo: </p><h1>GABRIEL</h1><h4>«¡Saludos, mujer favorecida! ¡El Señor está contigo!*».</h4><p>   <u>29</u>Confusa y perturbada, María trató de pensar lo que el ángel quería decir.</p><h1>GABRIEL</h1><h4> <u>30</u>—No tengas miedo, María </h4><p>—le dijo el ángel—, </p><h1>GABRIEL</h1><h4>¡porque has hallado el favor de Dios! <u>31</u>Concebirás y darás a luz un hijo, y le pondrás por nombre Jesús. <u>32</u>Él será muy grande y lo llamarán Hijo del Altísimo. El Señor Dios le dará el trono de su antepasado David. <u>33</u>Y reinará sobre Israel* para siempre; ¡su reino no tendrá fin!</h4><h1>MARÍA MADRE DE JESÚS</h1><h4> <u>34</u>—¿Pero cómo podrá suceder esto? </h4><p>—le preguntó María al ángel—. </p><h1>MARÍA MADRE DE JESÚS</h1><h4>Soy virgen.</h4><p>   <u>35</u>El ángel le contestó:</p><h1>GABRIEL</h1><h4> —El Espíritu Santo vendrá sobre ti, y el poder del Altísimo te cubrirá con su sombra. Por lo tanto, el bebé que nacerá será santo y será llamado Hijo de Dios. <u>36</u>Además, tu parienta Elisabet, ¡quedó embarazada en su vejez! Antes la gente decía que ella era estéril, pero ha concebido un hijo y ya está en su sexto mes de embarazo. <u>37</u>Pues la palabra de Dios nunca dejará de cumplirse.*</h4><p>   <u>38</u>María respondió:</p><h1>MARÍA MADRE DE JESÚS</h1><h4> —Soy la sierva del Señor. Que se cumpla todo lo que has dicho acerca de mí.</h4><p>   Y el ángel la dejó.<br />   <u>39</u>Pocos días después, María fue de prisa a la zona montañosa de Judea, al pueblo <u>40</u>donde vivía Zacarías. Entró en la casa y saludó a Elisabet. <u>41</u>Al escuchar el saludo de María, el bebé de Elisabet saltó en su vientre y Elisabet se llenó del Espíritu Santo.<br />   <u>42</u>Elisabet dio un grito de alegría y le exclamó a María:</p><h1>ELISABET</h1><h4> —Dios te ha bendecido más que a todas las mujeres, y tu hijo es bendito. <u>43</u>¿Por qué tengo este honor, que la madre de mi Señor venga a visitarme? <u>44</u>Cuando escuché tu saludo, el bebé saltó de alegría en mi vientre. <u>45</u>Eres bendita porque creíste que el Señor haría lo que te dijo.</h4><p>   <u>46</u>María respondió:</p><h1>MARÍA MADRE DE JESÚS</h1><h4> —Oh, cuánto alaba mi alma al Señor.<br />   <u>47</u> ¡Cuánto mi espíritu se alegra en Dios mi Salvador!<br />   <u>48</u>Pues se fijó en su humilde sierva,<br />   y de ahora en adelante todas las generaciones me llamarán bendita.<br />   <u>49</u>Pues el Poderoso es santo<br />   y ha hecho grandes cosas por mí.<br />   <u>50</u>Él muestra misericordia de generación en generación<br />   a todos los que le temen.<br />   <u>51</u>¡Su brazo poderoso ha hecho cosas tremendas!<br />   Dispersó a los orgullosos y a los altaneros.<br />   <u>52</u>A príncipes derrocó de sus tronos<br />   y exaltó a los humildes.<br />   <u>53</u>Al hambriento llenó de cosas buenas<br />   y a los ricos despidió con las manos vacías.<br />   <u>54</u>Ayudó a su siervo Israel<br />   y no se olvidó de ser misericordioso.<br />   <u>55</u>Pues lo prometió a nuestros antepasados,<br />   a Abraham y a sus descendientes para siempre.</h4><p>   <u>56</u>Y María se quedó con Elisabet unos tres meses y luego regresó a su casa.<br />   <u>57</u>Cuando se cumplió el tiempo para que naciera el bebé, Elisabet dio a luz un hijo varón. <u>58</u>Todos sus vecinos y parientes se alegraron al enterarse de que el Señor había sido tan misericordioso con ella.<br />   <u>59</u>Cuando el bebé cumplió ocho días, todos se reunieron para la ceremonia de circuncisión. Querían ponerle por nombre Zacarías como su padre, <u>60</u>pero Elisabet dijo:</p><h1>ELISABET</h1><h4> —¡No! ¡Su nombre es Juan!</h4><h1>LOS VECINOS DE ELISABET</h1><h4> <u>61</u>—¿Cómo?</h4><p>—exclamaron—. </p><h1>LOS VECINOS DE ELISABET</h1><h4>No hay nadie en tu familia con ese nombre.</h4><p>   <u>62</u>Entonces, le preguntaron por gestos al padre cómo quería que se llamara. <u>63</u>Zacarías pidió con señas que le dieran una tablilla para escribir y, para sorpresa de todos, escribió: «Su nombre es Juan». <u>64</u>Al instante Zacarías pudo hablar de nuevo y comenzó a alabar a Dios.<br />   <u>65</u>Todo el vecindario se llenó de temor reverente, y la noticia de lo que había sucedido corrió por todas las colinas de Judea. <u>66</u>Los que la oían meditaban sobre los acontecimientos y se preguntaban: </p><h1>GENTE EN JUDEA</h1><h4>«¿Qué llegará a ser este niño?». </h4><p>Pues la mano del Señor estaba sobre él de una manera especial.<br />   <u>67</u>Entonces su padre, Zacarías, se llenó del Espíritu Santo y dio la siguiente profecía:</p><h1>ZACARÍAS</h1><h4> <u>68</u>«Alaben al Señor, el Dios de Israel,<br />   porque ha visitado y redimido a su pueblo.<br />   <u>69</u>Nos envió un poderoso Salvador*<br />   del linaje real de su siervo David,<br />   <u>70</u>como lo prometió<br />   mediante sus santos profetas hace mucho tiempo.<br />   <u>71</u>Ahora seremos rescatados de nuestros enemigos<br />   y de todos los que nos odian.<br />   <u>72</u>Él ha sido misericordioso con nuestros antepasados<br />   al recordar su pacto sagrado,<br />   <u>73</u>el pacto que prometió mediante un juramento<br />   a nuestro antepasado Abraham.<br />   <u>74</u>Hemos sido rescatados de nuestros enemigos<br />   para poder servir a Dios sin temor,<br />   <u>75</u>en santidad y justicia,<br />   mientras vivamos.<br />   <u>76</u>»Y tú, mi pequeño hijo,<br />   serás llamado profeta del Altísimo,<br />   porque prepararás el camino para el Señor.<br />   <u>77</u>Dirás a su pueblo cómo encontrar la salvación<br />   mediante el perdón de sus pecados.<br />   <u>78</u>Gracias a la tierna misericordia de Dios,<br />   la luz matinal del cielo está a punto de brillar entre nosotros,*<br />   <u>79</u>para dar luz a los que están en oscuridad y en sombra de muerte,<br />   y para guiarnos al camino de la paz».</h4><p>   <u>80</u>Juan creció y se fortaleció en espíritu. Y vivió en el desierto hasta que comenzó su ministerio público a Israel.<br />   <strong>2</strong><u>1</u>En esos días, Augusto, el emperador de Roma, decretó que se hiciera un censo en todo el Imperio romano. <u>2</u>(Este fue el primer censo que se hizo cuando Cirenio era gobernador de Siria). <u>3</u>Todos regresaron a los pueblos de sus antepasados a fin de inscribirse para el censo. <u>4</u>Como José era descendiente del rey David, tuvo que ir a Belén de Judea, el antiguo hogar de David. Viajó hacia allí desde la aldea de Nazaret de Galilea. <u>5</u>Llevó consigo a María, su prometida, cuyo embarazo ya estaba avanzado.<br />   <u>6</u>Mientras estaban allí, llegó el momento para que naciera el bebé. <u>7</u>María dio a luz a su primer hijo, un varón. Lo envolvió en tiras de tela y lo acostó en un pesebre, porque no había alojamiento disponible para ellos.<br />   <u>8</u>Esa noche había unos pastores en los campos cercanos, que estaban cuidando sus rebaños de ovejas. <u>9</u>De repente, apareció entre ellos un ángel del Señor, y el resplandor de la gloria del Señor los rodeó. Los pastores estaban aterrados, <u>10</u>pero el ángel los tranquilizó. </p><h1>UN ÁNGEL</h1><h4>«No tengan miedo </h4><p>—dijo—. </p><h1>UN ÁNGEL</h1><h4>Les traigo buenas noticias que darán gran alegría a toda la gente. <u>11</u>¡El Salvador —sí, el Mesías, el Señor— ha nacido hoy en Belén, la ciudad de David! <u>12</u>Y lo reconocerán por la siguiente señal: encontrarán a un niño envuelto en tiras de tela, acostado en un pesebre».</h4><p>   <u>13</u>De pronto, se unió a ese ángel una inmensa multitud —los ejércitos celestiales— que alababan a Dios y decían:</p><h1>LOS EJÉRCITOS CELESTIALES</h1><h4> <u>14</u>«Gloria a Dios en el cielo más alto<br />   y paz en la tierra para aquellos en quienes Dios se complace».</h4><p>   <u>15</u>Cuando los ángeles regresaron al cielo, los pastores se dijeron unos a otros: </p><h1>PASTORES CERCA DE BELÉN</h1><h4>«¡Vayamos a Belén! Veamos esto que ha sucedido y que el Señor nos anunció».</h4><p>   <u>16</u>Fueron de prisa a la aldea y encontraron a María y a José. Y allí estaba el niño, acostado en el pesebre. <u>17</u>Después de verlo, los pastores contaron a todos lo que había sucedido y lo que el ángel les había dicho acerca del niño. <u>18</u>Todos los que escucharon el relato de los pastores quedaron asombrados, <u>19</u>pero María guardaba todas estas cosas en el corazón y pensaba en ellas con frecuencia. <u>20</u>Los pastores regresaron a sus rebaños, glorificando y alabando a Dios por lo que habían visto y oído. Todo sucedió tal como el ángel les había dicho.<br />   <u>21</u>Ocho días después, cuando el bebé fue circuncidado, le pusieron por nombre Jesús, el nombre que había dado el ángel aun antes de que el niño fuera concebido.<br />   <u>22</u>Luego llegó el tiempo para la ofrenda de purificación, como exigía la ley de Moisés después del nacimiento de un niño; así que sus padres lo llevaron a Jerusalén para presentarlo al Señor. <u>23</u>La ley del Señor dice: «Si el primer hijo de una mujer es varón, habrá que dedicarlo al Señor»*. <u>24</u>Así que ellos ofrecieron el sacrificio requerido en la ley del Señor, que consistía en «un par de tórtolas o dos pichones de paloma»*.<br />   <u>25</u>En ese tiempo, había en Jerusalén un hombre llamado Simeón. Era justo y devoto, y esperaba con anhelo que llegara el Mesías y rescatara a Israel. El Espíritu Santo estaba sobre él <u>26</u>y le había revelado que no moriría sin antes ver al Mesías del Señor. <u>27</u>Ese día, el Espíritu lo guió al templo. De manera que, cuando María y José llegaron para presentar al bebé Jesús ante el Señor como exigía la ley, <u>28</u>Simeón estaba allí. Tomó al niño en sus brazos y alabó a Dios diciendo:<br />   <u>29 </u></p><h1>SIMEÓN</h1><h4>«Señor Soberano, permite ahora que tu siervo muera en paz,<br />   como prometiste.<br />   <u>30</u>He visto tu salvación,<br />   <u>31</u> la que preparaste para toda la gente.<br />   <u>32</u>Él es una luz para revelar a Dios a las naciones,<br />   ¡y es la gloria de tu pueblo Israel!».</h4><p>   <u>33</u>Los padres de Jesús estaban asombrados de lo que se decía de él. <u>34</u>Entonces Simeón les dio su bendición y le dijo a María, la madre del bebé: </p><h1>SIMEÓN</h1><h4>«Este niño está destinado a provocar la caída de muchos en Israel, pero también será la alegría de muchos otros. Fue enviado como una señal de Dios, pero muchos se le opondrán. <u>35</u>Como resultado, saldrán a la luz los pensamientos más profundos de muchos corazones, y una espada atravesará tu propia alma».</h4><p>   <u>36</u>En el templo también estaba Ana, una profetisa muy anciana, hija de Fanuel, de la tribu de Aser. Su esposo había muerto cuando solo llevaban siete años de casados. <u>37</u>Después ella vivió como viuda hasta la edad de ochenta y cuatro años.* Nunca salía del templo, sino que permanecía allí de día y de noche adorando a Dios en ayuno y oración. <u>38</u>Llegó justo en el momento que Simeón hablaba con María y José, y comenzó a alabar a Dios. Habló del niño a todos los que esperaban que Dios rescatara a Jerusalén.<br />   <u>39</u>Una vez que los padres de Jesús cumplieron con todas las exigencias de la ley del Señor, regresaron a su casa en Nazaret de Galilea. <u>40</u>Allí el niño crecía sano y fuerte. Estaba lleno de sabiduría, y el favor de Dios estaba sobre él.</p><h5> 1:2 En griego los que, desde un principio, fueron siervos de la palabra.<br />   1:15 O aun desde su nacimiento.<br />   1:17a En griego esta palabra se refiere solo a los hombres.<br />   1:17b Ver Ml 4:5-6.<br />   1:28 Algunos manuscritos agregan Bendita eres entre las mujeres.<br />   1:33 En griego sobre la casa de Jacob.<br />   1:37 Algunos manuscritos dicen Pues nada es imposible para Dios.<br />   1:69 En griego Levantó un cuerno de salvación para nosotros.<br />   1:78 O la Luz Matinal del Cielo está a punto de visitarnos.<br />   2:23 Ex 13:2.<br />   2:24 Lv 12:8.<br />   2:37 O Ella había sido viuda por ochenta y cuatro años.</h5>","path":"/326","Question1":"Comparar es asociar dos o más personas, ideas o situaciones similares. ¿Puedes descubrir algunas comparaciones hechas por el autor de esta historia? ¿Por qué piensas que el autor hubiera hecho esta comparación?","Question2":"Contrastar es poner lado a lado does o más personas, ideas, o situaciones distintas. ¿Puedes descubrir algunos contrastes hechos por el autor en esta historia? ¿Por qué piensas que el autor hubiera hecho estos contrastes?","Question3":"Toma tiempo para notar las palabras o conceptos repetidos que has encontrado en esta historia","Question4":"Por favor toma tiempo para escribir una oración corta a Dis en respuesta a lo que haz descubierto mediante estas comparaciones, contrastes y repeticiones","prevPath":"/325","nextPath":"/327"}},"pathContext":{}}