{"data":{"postsJson":{"title":"El Arresto de Pablo en Jerusalén","questionsTitle":"ABRIENDO LA PALABRA","display":"block","bookName":"Hechos","ref":"21:17-23:11","html":"<p>   <strong>21</strong><u>17</u>Cuando llegamos, los hermanos de Jerusalén nos dieron una calurosa bienvenida.<br />   <u>18</u>Al día siguiente, Pablo fue con nosotros para encontrarnos con Santiago, y todos los ancianos de la iglesia de Jerusalén estaban presentes. <u>19</u>Después de saludarlos, Pablo dio un informe detallado de las cosas que Dios había realizado entre los gentiles mediante su ministerio.<br />   <u>20</u>Después de oírlo, alabaron a Dios. Luego dijeron: </p><h1>SANTIAGO HERMANO DE JESÚS &amp; LOS ANCIANOS DE LA IGLESIA</h1><h4>«Tú sabes, querido hermano, cuántos miles de judíos también han creído, y todos ellos siguen muy en serio la ley de Moisés; <u>21</u>pero se les ha dicho a los creyentes judíos de aquí, de Jerusalén, que tú enseñas a todos los judíos que viven entre los gentiles que abandonen la ley de Moisés. Ellos han oído que les enseñas que no circunciden a sus hijos ni que practiquen otras costumbres judías. <u>22</u>¿Qué debemos hacer? Seguramente se van a enterar de tu llegada.<br />   <u>23</u>»Queremos que hagas lo siguiente: hay entre nosotros cuatro hombres que han cumplido su voto; <u>24</u>acompáñalos al templo y participa con ellos en la ceremonia de purificación, y paga tú los gastos para que se rapen la cabeza según el ritual judío. Entonces todos sabrán que los rumores son falsos y que tú mismo cumples las leyes judías.<br />   <u>25</u>»En cuanto a los creyentes gentiles, ellos deben hacer lo que ya les dijimos en una carta: abstenerse de comer alimentos ofrecidos a ídolos, de consumir sangre o la carne de animales estrangulados, y de la inmoralidad sexual».</h4><p>   <u>26</u>Así que, al día siguiente, Pablo fue al templo con los otros hombres. Ya comenzado el ritual de purificación, anunció públicamente la fecha en que se cumpliría el tiempo de los votos y se ofrecerían sacrificios por cada uno de los hombres.<br />   <u>27</u>Cuando estaban por cumplirse los siete días del voto, unos judíos de la provincia de Asia vieron a Pablo en el templo e incitaron a una turba en su contra. Lo agarraron <u>28</u>mientras gritaban: </p><h1>LOS JUDÍOS DE ASIA</h1><h4>«¡Hombres de Israel, ayúdennos! Este es el hombre que predica en contra de nuestro pueblo en todas partes y les dice a todos que desobedezcan las leyes judías. Habla en contra del templo, ¡y hasta profana este lugar santo llevando gentiles* adentro!». </h4><p><u>29</u>(Pues más temprano ese mismo día lo habían visto en la ciudad con Trófimo, un gentil de Éfeso,* y supusieron que Pablo lo había llevado al templo).<br />   <u>30</u>Toda la ciudad fue estremecida por estas acusaciones y se desencadenó un gran disturbio. Agarraron a Pablo y lo arrastraron fuera del templo e inmediatamente cerraron las puertas detrás de él. <u>31</u>Cuando estaban a punto de matarlo, le llegó al comandante del regimiento romano la noticia de que toda Jerusalén estaba alborotada. <u>32</u>De inmediato el comandante llamó a sus soldados y oficiales* y corrió entre la multitud. Cuando la turba vio que venían el comandante y las tropas, dejaron de golpear a Pablo.<br />   <u>33</u>Luego el comandante lo arrestó y ordenó que lo sujetaran con dos cadenas. Le preguntó a la multitud quién era él y qué había hecho. <u>34</u>Unos gritaban una cosa, y otros otra. Como no pudo averiguar la verdad entre todo el alboroto y la confusión, ordenó que llevaran a Pablo a la fortaleza. <u>35</u>Cuando Pablo llegó a las escaleras, la turba se puso tan violenta que los soldados tuvieron que levantarlo sobre sus hombros para protegerlo. <u>36</u>Y la multitud seguía gritando desde atrás: </p><h1>UNA MULTITUD EN JERUSALÉN</h1><h4>«¡Mátenlo! ¡Mátenlo!».</h4><p>   <u>37</u>Cuando estaban por llevarlo adentro, Pablo le dijo al comandante:</p><h1>PABLO</h1><h3> —¿Puedo hablar con usted?</h3><h1>CLAUDIO LISIAS</h1><h4> —¿¡Hablas griego!? </h4><p>—le preguntó el comandante, sorprendido—. </p><h1>CLAUDIO LISIAS</h1><h4><u>38</u>¿No eres tú el egipcio que encabezó una rebelión hace un tiempo y llevó al desierto a cuatro mil miembros del grupo llamado “Los Asesinos”?</h4><h1>PABLO</h1><h3> <u>39</u>—No </h3><p>—contestó Pablo—, </p><h1>PABLO</h1><h3>soy judío y ciudadano de Tarso de Cilicia, que es una ciudad importante. Por favor, permítame hablar con esta gente.</h3><p>   <u>40</u>El comandante estuvo de acuerdo, entonces Pablo se puso de pie en las escaleras e hizo señas para pedir silencio. Pronto un gran silencio envolvió a la multitud, y Pablo se dirigió a la gente en su propia lengua, en arameo.*</p><h1>PABLO</h1><h3> <strong>22</strong><u>1</u>«Hermanos y estimados padres </h3><p>—dijo Pablo—, </p><h1>PABLO</h1><h3>escuchen mientras presento mi defensa». </h3><p><u>2</u>Cuando lo oyeron hablar en el idioma de ellos,* el silencio fue aún mayor.<br />   <u>3</u>Entonces Pablo dijo: </p><h1>PABLO</h1><h3>«Soy judío, nacido en Tarso, una ciudad de Cilicia, y fui criado y educado aquí en Jerusalén bajo el maestro Gamaliel. Como estudiante de él, fui cuidadosamente entrenado en nuestras leyes y costumbres judías. Llegué a tener un gran celo por honrar a Dios en todo lo que hacía, tal como todos ustedes hoy. <u>4</u>Perseguí a los seguidores del Camino, acosando a algunos hasta la muerte, y arresté tanto a hombres como a mujeres para arrojarlos en la cárcel. <u>5</u>El sumo sacerdote y todo el consejo de ancianos pueden dar fe de que esto es cierto. Pues recibí cartas de ellos, dirigidas a nuestros hermanos judíos en Damasco, las cuales me autorizaban a encadenar a los seguidores del Camino de esa ciudad y traerlos a Jerusalén para que fueran castigados.<br />   <u>6</u>»Cuando iba de camino, ya cerca de Damasco, como al mediodía, de repente una intensa luz del cielo brilló alrededor de mí. <u>7</u>Caí al suelo y oí una voz que me decía: “Saulo, Saulo, ¿por qué me persigues?”.<br />   <u>8</u>»“¿Quién eres, señor?”, pregunté.<br />   »Y la voz contestó: “Yo soy Jesús de Nazaret,* a quien tú persigues”. <u>9</u>La gente que iba conmigo vio la luz pero no entendió la voz que me hablaba.<br />   <u>10</u>»Yo pregunté: “¿Qué debo hacer, Señor?”.<br />   »Y el Señor me dijo: “Levántate y entra en Damasco, allí se te dirá todo lo que debes hacer”.<br />   <u>11</u>»Quedé ciego por la intensa luz y mis compañeros tuvieron que llevarme de la mano hasta Damasco. <u>12</u>Allí vivía un hombre llamado Ananías. Era un hombre recto, muy devoto de la ley y muy respetado por todos los judíos de Damasco. <u>13</u>Él llegó y se puso a mi lado y me dijo: “Hermano Saulo, recobra la vista”. Y, en ese mismo instante, ¡pude verlo!<br />   <u>14</u>»Después me dijo: “El Dios de nuestros antepasados te ha escogido para que conozcas su voluntad y para que veas al Justo y lo oigas hablar. <u>15</u>Pues tú serás su testigo; les contarás a todos lo que has visto y oído. <u>16</u>¿Qué esperas? Levántate y bautízate. Queda limpio de tus pecados al invocar el nombre del Señor”.<br />   <u>17</u>»Después de regresar a Jerusalén y, mientras oraba en el templo, caí en un estado de éxtasis. <u>18</u>Tuve una visión de Jesús,* quien me decía: “¡Date prisa! Sal de Jerusalén, porque la gente de aquí no aceptará tu testimonio acerca de mí”.<br />   <u>19</u>»“Pero Señor —argumenté—, seguramente ellos saben que, en cada sinagoga, yo encarcelé y golpeé a los que creían en ti. <u>20</u>Y estuve totalmente de acuerdo cuando mataron a tu testigo Esteban. Estuve allí cuidando los abrigos que se quitaron cuando lo apedrearon”.<br />   <u>21</u>»Pero el Señor me dijo: “¡Ve, porque yo te enviaré lejos, a los gentiles*!”».</h3><p>   <u>22</u>La multitud escuchó hasta que Pablo dijo esta palabra. Entonces todos comenzaron a gritar: </p><h1>UNA MULTITUD EN JERUSALÉN</h1><h4>«¡Llévense a ese tipo! ¡No es digno de vivir!». </h4><p><u>23</u>Gritaron, arrojaron sus abrigos y lanzaron puñados de polvo al aire.<br />   <u>24</u>El comandante llevó a Pablo adentro y ordenó que lo azotaran con látigos para hacerlo confesar su delito. Quería averiguar por qué la multitud se había enfurecido. <u>25</u>Cuando ataron a Pablo para azotarlo, Pablo le preguntó al oficial* que estaba allí:</p><h1>PABLO</h1><h3> —¿Es legal que azoten a un ciudadano romano que todavía no ha sido juzgado?</h3><p>   <u>26</u>Cuando el oficial oyó esto, fue al comandante y le preguntó: </p><h1>UN OFICIAL ROMANO</h1><h4>«¿Qué está haciendo? ¡Este hombre es un ciudadano romano!».</h4><p>   <u>27</u>Entonces el comandante se acercó a Pablo y le preguntó:</p><h1>CLAUDIO LISIAS</h1><h4> —Dime, ¿eres ciudadano romano?</h4><h1>PABLO</h1><h3> —Sí, por supuesto que lo soy </h3><p>—respondió Pablo.</p><h1>CLAUDIO LISIAS</h1><h4> <u>28</u>—Yo también lo soy </h4><p>—dijo el comandante entre dientes—, </p><h1>CLAUDIO LISIAS</h1><h4>¡y me costó mucho dinero!</h4><p>   Pablo respondió:</p><h1>PABLO</h1><h3> —¡Pero yo soy ciudadano de nacimiento!</h3><p>   <u>29</u>Los soldados que estaban a punto de interrogar a Pablo se retiraron velozmente cuando se enteraron de que era ciudadano romano, y el comandante quedó asustado porque había ordenado que lo amarraran y lo azotaran.<br />   <u>30</u>Al día siguiente, el comandante ordenó que los sacerdotes principales se reunieran en sesión con el Concilio Supremo judío.* Quería averiguar de qué se trataba el problema, así que soltó a Pablo para presentarlo delante de ellos.<br />   <strong>23</strong><u>1</u>Mirando fijamente al Concilio Supremo,* Pablo comenzó: </p><h1>PABLO</h1><h3>«Hermanos, ¡siempre he vivido ante Dios con la conciencia limpia!».</h3><p>   <u>2</u>Al instante, Ananías, el sumo sacerdote, ordenó a los que estaban cerca de Pablo que lo golpearan en la boca. <u>3</u>Pero Pablo le dijo: </p><h1>PABLO</h1><h3>«¡Dios te golpeará a ti, hipócrita corrupto!* ¿Qué clase de juez eres si tú mismo infringes la ley al ordenar que me golpeen así?».</h3><p>   <u>4</u>Los que estaban cerca de Pablo, le dijeron:</p><h1>LOS LÍDERES JUDÍOS</h1><h4> —¿Te atreves a insultar al sumo sacerdote de Dios?</h4><h1>PABLO</h1><h3> <u>5</u>—Lo siento, hermanos. No me había dado cuenta de que él es el sumo sacerdote </h3><p>—contestó Pablo—, porque las Escrituras dicen: “No hables mal de ninguno de tus gobernantes”*.<br />   <u>6</u>Pablo se dio cuenta de que algunos miembros del Concilio Supremo eran saduceos y que otros eran fariseos, por lo tanto, gritó: </p><h1>PABLO</h1><h3>«Hermanos, ¡yo soy fariseo, al igual que mis antepasados! ¡Y estoy en juicio porque mi esperanza está en la resurrección de los muertos!».</h3><p>   <u>7</u>Esto dividió al Concilio —puso a los fariseos contra los saduceos—, <u>8</u>porque los saduceos dicen que no hay resurrección, ni ángeles, ni espíritus, pero los fariseos sí creen en todo esto. <u>9</u>Así que hubo un gran alboroto. Algunos de los maestros de la ley religiosa que eran fariseos se levantaron de un salto y comenzaron a discutir enérgicamente. </p><h1>LOS FARISEOS</h1><h4>«Nosotros no encontramos nada malo en él </h4><p>—gritaban—. </p><h1>LOS FARISEOS</h1><h4>Tal vez algún espíritu o ángel le habló». </h4><p><u>10</u>Como el conflicto se tornó más violento, el comandante tenía temor de que descuartizaran a Pablo. De modo que les ordenó a sus soldados que fueran a rescatarlo por la fuerza y lo regresaran a la fortaleza.<br />   <u>11</u>Esa noche el Señor se le apareció a Pablo y le dijo: </p><h1>DIOS</h1><h2>«Ten ánimo, Pablo. Así como has sido mi testigo aquí en Jerusalén, también debes predicar la Buena Noticia en Roma».</h2><h5> 21:28 En griego griegos.<br />   21:29 En griego Trófimo, el efesio.<br />   21:32 En griego centuriones.<br />   21:40 O hebreo.<br />   22:2 En griego en arameo, o en hebreo.<br />   22:8 O Jesús nazareno.<br />   22:18 En griego de él.<br />   22:21 Gentil[es], que no es judío.<br />   22:25 En griego centurión; también en 22:26.<br />   22:30 En griego el Sanedrín.<br />   23:1 En griego al Sanedrín; similar en 23:6, 15, 20, 28.<br />   23:3 En griego a ti, pared blanqueada.<br />   23:5 Ex 22:28.</h5>","path":"/361","Question1":"¿Qué te gusta acerca de esta porción de la Escritura/las Escrituras?","Question2":"¿Qué puedes observar acerca de los caminos/maneras de Dios?","Question3":"¿Qué observas acerca de los personajes principales en esta porción de las Escrituras?","Question4":"¿Cómo quieres responder a la luz de estas observaciones?","prevPath":"/360","nextPath":"/362"}},"pathContext":{}}