{"data":{"postsJson":{"title":"Las Siete Copas","questionsTitle":"HAMBRIENTO POR CONOCER MÁS A DIOS","display":"block","bookName":"Apocalipsis","ref":"15:1-16:21","html":"<p>   <strong>15</strong><u>1</u>Luego vi en el cielo otro maravilloso suceso de gran importancia. Siete ángeles sostenían las últimas siete plagas, que completarían la ira de Dios. <u>2</u>Vi delante de mí algo que parecía un mar de cristal mezclado con fuego. Sobre este mar estaban de pie todos los que habían vencido a la bestia, a su estatua y al número que representa su nombre. Todos tenían arpas que Dios les había dado <u>3</u>y entonaban el canto de Moisés, siervo de Dios, y el canto del Cordero:<br />   </p><h1>TODOS LOS REDIMIDOS</h1><h4>«Grandes y maravillosas son tus obras,<br />   oh Señor Dios, el Todopoderoso.<br />   Justos y verdaderos son tus caminos,<br />   oh Rey de las naciones.*<br />   <u>4</u>¿Quién no te temerá, Señor,<br />   y glorificará tu nombre?<br />   Pues solo tú eres santo.<br />   Todas las naciones vendrán y adorarán delante de ti,<br />   porque tus obras de justicia han sido reveladas».</h4><p>   <u>5</u>Luego miré y vi que se abría por completo el templo que está en el cielo, el tabernáculo de Dios. <u>6</u>Los siete ángeles que sostenían las siete plagas salieron del templo. Estaban vestidos de un lino blanco* sin mancha alguna y tenían una banda de oro que cruzaba el pecho. <u>7</u>Entonces uno de los cuatro seres vivientes le entregó a cada uno de los siete ángeles una copa de oro llena de la ira de Dios, quien vive por siempre y para siempre. <u>8</u>El templo se llenó del humo de la gloria y el poder de Dios. Nadie podía entrar en el templo hasta que los siete ángeles terminaran de derramar las siete plagas.<br />   <strong>16</strong><u>1</u>Luego oí una voz potente que venía del templo y decía a los siete ángeles: </p><h1>DIOS</h1><h2>«Vayan y derramen sobre la tierra las siete copas que contienen la ira de Dios».</h2><p>   <u>2</u>Así que el primer ángel salió del templo y derramó su copa sobre la tierra, y a todos los que tenían la marca de la bestia y que adoraban a su estatua les salieron horribles llagas malignas.<br />   <u>3</u>Después el segundo ángel derramó su copa sobre el mar, y el agua se volvió como la sangre de un cadáver, y murió todo lo que estaba en el mar.<br />   <u>4</u>Entonces el tercer ángel derramó su copa sobre los ríos y los manantiales, y estos se convirtieron en sangre. <u>5</u>Y oí que el ángel que tenía autoridad sobre todas las aguas decía:</p><h1>EL TERCER ÁNGEL</h1><h4> «Oh Santo, el que es y que siempre era, tú eres justo,<br />   porque has enviado estos juicios.<br />   <u>6</u>Como derramaron la sangre<br />   de tu pueblo santo y de tus profetas,<br />   tú les has dado a beber sangre.<br />   Es su justa recompensa».</h4><p>   <u>7</u>Y oí una voz que venía del altar y* decía:</p><h1>DIOS</h1><h2> «Sí, oh Señor Dios, el Todopoderoso,<br />   tus juicios son verdaderos y justos».</h2><p>   <u>8</u>Entonces el cuarto ángel derramó su copa sobre el sol, esto hacía que quemara a todos con su fuego. <u>9</u>Todos sufrieron quemaduras debido a la descarga de calor y maldijeron el nombre de Dios, quien tenía control sobre todas estas plagas. No se arrepintieron de sus pecados ni se volvieron a Dios ni le dieron la gloria.<br />   <u>10</u>Después el quinto ángel derramó su copa sobre el trono de la bestia, y el reino de la bestia quedó sumergido en la oscuridad. Sus súbditos rechinaban los dientes* por la angustia <u>11</u>y maldecían al Dios del cielo por los dolores y las llagas, pero no se arrepintieron de sus fechorías ni volvieron a Dios.<br />   <u>12</u>Luego el sexto ángel derramó su copa sobre el gran río Éufrates, y este se secó para que los reyes del oriente pudieran marchar con sus ejércitos sin obstáculos hacia el occidente. <u>13</u>Y vi que de la boca del dragón, de la boca de la bestia y de la boca del falso profeta saltaban tres espíritus malignos* que parecían ranas. <u>14</u>Estos son espíritus de demonios que hacen milagros y salen a reunir a todos los gobernantes del mundo para pelear contra el Señor en la batalla del gran día del juicio de Dios, el Todopoderoso.</p><h1>DIOS</h1><h2> <u>15</u>«Miren, ¡yo vendré como un ladrón, cuando nadie lo espere! Benditos son todos los que me esperan y tienen su ropa lista para no tener que andar desnudos y avergonzados».</h2><p>   <u>16</u>Y los espíritus de demonios reunieron a todos los gobernantes y a sus ejércitos en un lugar que en hebreo se llama Armagedón.*<br />   <u>17</u>Luego el séptimo ángel derramó su copa en el aire, y desde el trono del templo salió un fuerte grito: </p><h1>DIOS</h1><h2>«¡Todo ha terminado!». </h2><p><u>18</u>Entonces rugieron y retumbaron truenos, y salieron relámpagos; y se produjo un fuerte terremoto, el peor desde que el hombre fue puesto sobre la tierra. <u>19</u>La gran ciudad de Babilonia se partió en tres secciones, y las ciudades de muchas naciones cayeron y quedaron reducidas a escombros. Así que Dios se acordó de todos los pecados de Babilonia, y la hizo beber de la copa que estaba llena del vino del furor de su ira. <u>20</u>Entonces desaparecieron todas las islas, y las montañas se vinieron abajo y no existieron más. <u>21</u>Hubo una gran tormenta de granizo, y piedras de granizo, como de treinta y cuatro kilos* cada una, cayeron del cielo sobre las personas. Maldijeron a Dios debido a la terrible plaga de granizo.</p><h5> 15:3 Algunos manuscritos dicen Rey de los siglos.<br />   15:6 Otros manuscritos dicen vestidos de piedra blanca; incluso otros dicen vestidos con [prendas] blancas hechas de lino.<br />   16:7 En griego oí que el altar.<br />   16:10 En griego se mordían la lengua.<br />   16:13 En griego impuros.<br />   16:16 O Ar-Magedon.<br />   16:21 En griego un talento [75 libras].</h5>","path":"/429","Question1":"Toma nota de las Actos/Acciones de Dios descritas en esta historia","Question2":"¿Qué revelan estas acerca del carácter de Dios?","Question3":"¿Haz experimentado alguna vez esta dimensión del carácter de Dios en tu vida? Si es así, ¿cómo? Y si no, ¿cómo podrías llegar a experimentar esto?","Question4":"¿Qué puedes hacer para crecer en tu deseo de conocer y experimentar a Dios más intimamente hoy?","prevPath":"/428","nextPath":"/430"}},"pathContext":{}}